{
    "hid" : "0.32",
    "parameters" : 
    [
        {
            "id" : "P1",
            "name" : "$length_between_row [mm]",
            "unit" : null,
            "value" : 4.7249999999999996
        },
        {
            "id" : "P2",
            "name" : "$move_r [mm]",
            "unit" : null,
            "value" : 1.8000000000000007
        }
    ],
    "responses" : 
    [
        {
            "id" : "P3",
            "name" : "mean",
            "unit" : null,
            "value" : 0.1225653403358653
        },
        {
            "id" : "P4",
            "name" : "dif",
            "unit" : null,
            "value" : 0.084395550003825703
        }
    ]
}