{
    "hid" : "0.66",
    "parameters" : 
    [
        {
            "id" : "P1",
            "name" : "$length_between_row [mm]",
            "unit" : null,
            "value" : 3.125
        },
        {
            "id" : "P2",
            "name" : "$move_r [mm]",
            "unit" : null,
            "value" : 7.4000000000000004
        }
    ],
    "responses" : 
    [
        {
            "id" : "P3",
            "name" : "mean",
            "unit" : null,
            "value" : 0.094746647918467597
        },
        {
            "id" : "P4",
            "name" : "dif",
            "unit" : null,
            "value" : 0.01414135203659839
        }
    ]
}