{
    "hid" : "0.88",
    "parameters" : 
    [
        {
            "id" : "P1",
            "name" : "$length_between_row [mm]",
            "unit" : null,
            "value" : 2.6750000000000003
        },
        {
            "id" : "P2",
            "name" : "$move_r [mm]",
            "unit" : null,
            "value" : 20.600000000000001
        }
    ],
    "responses" : 
    [
        {
            "id" : "P3",
            "name" : "mean",
            "unit" : null,
            "value" : 0.048502104746750388
        },
        {
            "id" : "P4",
            "name" : "dif",
            "unit" : null,
            "value" : 0.0058921460883976694
        }
    ]
}